slack_app/__init__.py
slack_app/admin.py
slack_app/apps.py
slack_app/auth_backends.py
slack_app/decorators.py
slack_app/exceptions.py
slack_app/forms.py
slack_app/helpers.py
slack_app/models.py
slack_app/settings.py
slack_app/signals.py
slack_app/tasks.py
slack_app/urls.py
slack_app/views.py
slack_app/migrations/0001_initial.py
slack_app/migrations/__init__.py
slack_app/templates/slack_app/slack_base.html
slack_app/templates/slack_app/verified_nonce.html
django_slack_app-1.0.40.dist-info/LICENSE
django_slack_app-1.0.40.dist-info/METADATA
django_slack_app-1.0.40.dist-info/WHEEL
django_slack_app-1.0.40.dist-info/top_level.txt
django_slack_app-1.0.40.dist-info/RECORD
