Metadata-Version: 2.1
Name: django-slack-app
Version: 1.0.40
Summary: A Django app to help integrate Slack
Home-page: https://django-slack-integration.webscope.io
Author: Jan Vorcak
Author-email: vorcak@webscope.io
License: MIT
Platform: UNKNOWN
Classifier: Environment :: Web Environment
Classifier: Framework :: Django
Classifier: Intended Audience :: Developers
Classifier: Operating System :: OS Independent
Classifier: Programming Language :: Python
Classifier: Programming Language :: Python :: 3
Classifier: Programming Language :: Python :: 3 :: Only
Classifier: Programming Language :: Python :: 3.6
Classifier: Programming Language :: Python :: 3.7
Classifier: Programming Language :: Python :: 3.8
Requires-Dist: slackclient
Requires-Dist: celery
